MANIFEST.in
setup.cfg
setup.py
matialvarezs_node_configurations/__init__.py
matialvarezs_node_configurations/admin.py
matialvarezs_node_configurations/apps.py
matialvarezs_node_configurations/context_processors.py
matialvarezs_node_configurations/decorators.py
matialvarezs_node_configurations/definitions.py
matialvarezs_node_configurations/dispatcher.py
matialvarezs_node_configurations/errors.py
matialvarezs_node_configurations/initialize_table_configurations.py
matialvarezs_node_configurations/managers.py
matialvarezs_node_configurations/middlewares.py
matialvarezs_node_configurations/models.py
matialvarezs_node_configurations/serializers.py
matialvarezs_node_configurations/settings.py
matialvarezs_node_configurations/signals.py
matialvarezs_node_configurations/tests.py
matialvarezs_node_configurations/urls.py
matialvarezs_node_configurations/utils.py
matialvarezs_node_configurations/views.py
matialvarezs_node_configurations.egg-info/PKG-INFO
matialvarezs_node_configurations.egg-info/SOURCES.txt
matialvarezs_node_configurations.egg-info/dependency_links.txt
matialvarezs_node_configurations.egg-info/requires.txt
matialvarezs_node_configurations.egg-info/top_level.txt
matialvarezs_node_configurations/api/urls.py
matialvarezs_node_configurations/api/v1/decorators.py
matialvarezs_node_configurations/api/v1/dispatcher.py
matialvarezs_node_configurations/api/v1/errors.py
matialvarezs_node_configurations/api/v1/urls.py
matialvarezs_node_configurations/api/v1/views.py
matialvarezs_node_configurations/management/__init__.py
matialvarezs_node_configurations/management/commands/__init__.py
matialvarezs_node_configurations/management/commands/matialvarezs_node_configurations_initialize_table.py
matialvarezs_node_configurations/management/commands/matialvarezs_node_configurations_test_command.py
matialvarezs_node_configurations/migrations/0001_initial.py
matialvarezs_node_configurations/migrations/0002_auto_20190905_0228.py
matialvarezs_node_configurations/migrations/__init__.py
matialvarezs_node_configurations/migrations/__pycache__/0001_initial.cpython-35.pyc
matialvarezs_node_configurations/migrations/__pycache__/__init__.cpython-35.pyc