Metadata-Version: 1.1
Name: matialvarezs-node-configurations
Version: 0.0.24
Summary: Nodes configurations - model and api
Home-page: UNKNOWN
Author: Matias Alvarez Sabate
Author-email: matialvarezs@gmail.com
License: UNKNOWN
Platform: UNKNOWN
Classifier: Programming Language :: Python :: 3.5
